<?xml version="1.0" encoding="UTF-8"?>
<OpenSearchDescription xmlns="http://a9.com/-/spec/opensearch/1.1/" xmlns:moz="http://www.mozilla.org/2006/browser/search/">
  <ShortName>Konglig Fysiks Sångbok</ShortName>
  <Description>Sök i Konglig Fysiks Sångbok</Description>
  <Url type="text/html" method="get" template="https://f.kth.se/sangbok/#/search/{searchTerms}"/>
  <Image width="32" height="32">https://f.kth.se/sangbok/img/icons/favicon-32x32.png</Image>
  <Developer>F.dev</Developer>
  <InputEncoding>UTF-8</InputEncoding>
</OpenSearchDescription>